pidgey-1.0.4.dist-info/METADATA
pidgey-1.0.4.dist-info/WHEEL
pidgey-1.0.4.dist-info/entry_points.txt
pidgey-1.0.4.dist-info/licenses/LICENSE
pidgey/__init__.py
pidgey/agama_backend.py
pidgey/base.py
pidgey/gala_backend.py
pidgey/galpy_backend.py
pidgey-1.0.4.dist-info/RECORD
