Metadata-Version: 2.1
Name: pidgey
Version: 1.0.4
Summary: Python interface for the dynamics of galaxies. Uses agama, gala, and galpy as backends.
Author-Email: ilikecubesnstuff <25328250+ilikecubesnstuff@users.noreply.github.com>
License: MIT
Classifier: Intended Audience :: Science/Research
Classifier: Natural Language :: English
Classifier: License :: OSI Approved :: MIT License
Classifier: Programming Language :: Python :: 3 :: Only
Classifier: Programming Language :: Python :: 3.9
Classifier: Programming Language :: Python :: 3.10
Classifier: Programming Language :: Python :: 3.11
Classifier: Programming Language :: Python :: 3.12
Classifier: Topic :: Scientific/Engineering :: Astronomy
Classifier: Topic :: Scientific/Engineering :: Physics
Requires-Python: >=3.9
Requires-Dist: iext>=1
Requires-Dist: numpy>=1.22
Requires-Dist: astropy>=5
